{
  "Theme": "Ultimele știri",
  "Title": "Șantaj pe rețele de socializare: Patru bărbați au fost trimiși în judecată",
  "ImageUrl": "https://zugo.md/wp-content/uploads/2023/08/banner-3-390x220.png",
  "AltText": "Photo of Șantaj pe rețele de socializare: Patru bărbați au fost trimiși în judecată",
  "PublishTime": "4 zile în urmă",
  "ParseDate": "2024-10-12T11:14:49.3060518+03:00",
  "Content": "https://zugo.md/toate-stirile/șantaj-pe-retele-de-socializare-patru-barbati-au-fost-trimisi-in-judecata"
}