{
  "Theme": "Ultimele știri",
  "Title": "Victorie pentru naționala R. Moldova în meciul cu Andorra",
  "ImageUrl": "https://zugo.md/wp-content/uploads/2024/10/photo-1728580240-13-390x220.jpg",
  "AltText": "Photo of Victorie pentru naționala R. Moldova în meciul cu Andorra",
  "PublishTime": "o zi în urmă",
  "ParseDate": "2024-10-12T11:14:05.9371693+03:00",
  "Content": "Naționala Republicii Moldova a învins echipa Andorrei cu scorul de 2-0 în cel de-al doilea meci din Liga D, grupa 2, a Ligii Națiunilor.</strong> Meciul a avut loc pe 10 octombrie 2024, pe Stadionul Zimbru din Chișinău, în prezența a 6.442 de spectatori. Golurile partidei au fost înscrise de Artur Ioniță în minutul 31 și Maxim Cojocaru în prelungiri, în minutul 90+5. Cu acest rezultat, Republica Moldova acumulează punctaj maxim după două meciuri și urmează să dispute partida decisivă pentru promovarea în Liga C, în deplasare, împotriva Maltei, pe 13 octombrie. "
}